[
  {
    "name": "tester-8945",
    "from_zone": "any",
    "to_zone": "any",
    "source": "any",
    "destination": "any",
    "application": "any",
    "service": "application-default",
    "action": "allow",
    "log_start": "no",
    "log_end": "yes",
    "added_time": "2026/01/12 11:14:58"
  },
  {
    "name": "facebook-test123",
    "from_zone": "any",
    "to_zone": "any",
    "source": "any",
    "destination": "any",
    "application": "any",
    "service": "application-default",
    "action": "allow",
    "log_start": "no",
    "log_end": "yes",
    "added_time": "2026/01/10 16:45:30"
  },
  {
    "name": "test-rule-123",
    "from_zone": "any",
    "to_zone": "any",
    "source": "any",
    "destination": "any",
    "application": "any",
    "service": "application-default",
    "action": "allow",
    "log_start": "no",
    "log_end": "yes",
    "added_time": "2026/01/10 16:11:30"
  },
  {
    "name": "API-CREATED-TEST",
    "from_zone": "any",
    "to_zone": "any",
    "source": "any",
    "destination": "any",
    "application": "any",
    "service": "application-default",
    "action": "allow",
    "log_start": "no",
    "log_end": "yes",
    "added_time": "2026/01/10 10:40:43"
  }
]